{
  "tournamentBlockGame": {
    "id": 588,
    "items": [
      {
        "gameId": 3,
        "position": 1,
        "isActive": 0
      },
      {
        "gameId": 8,
        "position": 2,
        "isActive": 1
      },
      {
        "gameId": 9,
        "position": 3,
        "isActive": 1
      },
      {
        "gameId": 11,
        "position": 4,
        "isActive": 1
      },
      {
        "gameId": 13,
        "position": 5,
        "isActive": 1
      },
      {
        "gameId": 14,
        "position": 6,
        "isActive": 1
      },
      {
        "gameId": 15,
        "position": 7,
        "isActive": 1
      },
      {
        "gameId": 16,
        "position": 8,
        "isActive": 1
      },
      {
        "gameId": 17,
        "position": 9,
        "isActive": 1
      },
      {
        "gameId": 19,
        "position": 10,
        "isActive": 1
      },
      {
        "gameId": 20,
        "position": 11,
        "isActive": 1
      },
      {
        "gameId": 21,
        "position": 12,
        "isActive": 1
      },
      {
        "gameId": 22,
        "position": 13,
        "isActive": 1
      },
      {
        "gameId": 23,
        "position": 14,
        "isActive": 1
      },
      {
        "gameId": 24,
        "position": 15,
        "isActive": 1
      },
      {
        "gameId": 27,
        "position": 16,
        "isActive": 1
      },
      {
        "gameId": 28,
        "position": 17,
        "isActive": 1
      },
      {
        "gameId": 29,
        "position": 18,
        "isActive": 1
      },
      {
        "gameId": 31,
        "position": 19,
        "isActive": 1
      },
      {
        "gameId": 33,
        "position": 20,
        "isActive": 1
      },
      {
        "gameId": 34,
        "position": 21,
        "isActive": 1
      },
      {
        "gameId": 35,
        "position": 22,
        "isActive": 1
      },
      {
        "gameId": 36,
        "position": 23,
        "isActive": 1
      },
      {
        "gameId": 37,
        "position": 24,
        "isActive": 1
      },
      {
        "gameId": 39,
        "position": 25,
        "isActive": 1
      },
      {
        "gameId": 40,
        "position": 26,
        "isActive": 1
      },
      {
        "gameId": 41,
        "position": 27,
        "isActive": 1
      },
      {
        "gameId": 42,
        "position": 28,
        "isActive": 1
      },
      {
        "gameId": 1111,
        "position": 29,
        "isActive": 1
      },
      {
        "gameId": 1141,
        "position": 30,
        "isActive": 1
      },
      {
        "gameId": 1177,
        "position": 31,
        "isActive": 1
      },
      {
        "gameId": 3001,
        "position": 32,
        "isActive": 1
      },
      {
        "gameId": 3007,
        "position": 33,
        "isActive": 1
      },
      {
        "gameId": 3011,
        "position": 34,
        "isActive": 1
      },
      {
        "gameId": 3295,
        "position": 35,
        "isActive": 1
      },
      {
        "gameId": 3305,
        "position": 36,
        "isActive": 1
      },
      {
        "gameId": 3307,
        "position": 37,
        "isActive": 1
      },
      {
        "gameId": 3315,
        "position": 38,
        "isActive": 1
      },
      {
        "gameId": 3891,
        "position": 39,
        "isActive": 1
      },
      {
        "gameId": 16049,
        "position": 40,
        "isActive": 1
      },
      {
        "gameId": 17057,
        "position": 41,
        "isActive": 1
      },
      {
        "gameId": 19657,
        "position": 42,
        "isActive": 1
      },
      {
        "gameId": 19729,
        "position": 43,
        "isActive": 1
      },
      {
        "gameId": 19807,
        "position": 44,
        "isActive": 1
      },
      {
        "gameId": 19815,
        "position": 45,
        "isActive": 1
      },
      {
        "gameId": 22153,
        "position": 46,
        "isActive": 1
      },
      {
        "gameId": 22449,
        "position": 47,
        "isActive": 1
      },
      {
        "gameId": 35999,
        "position": 48,
        "isActive": 1
      },
      {
        "gameId": 36243,
        "position": 49,
        "isActive": 1
      },
      {
        "gameId": 39457,
        "position": 50,
        "isActive": 1
      },
      {
        "gameId": 41665,
        "position": 51,
        "isActive": 1
      },
      {
        "gameId": 42529,
        "position": 52,
        "isActive": 1
      },
      {
        "gameId": 43180,
        "position": 53,
        "isActive": 1
      },
      {
        "gameId": 43760,
        "position": 54,
        "isActive": 1
      },
      {
        "gameId": 43834,
        "position": 55,
        "isActive": 1
      },
      {
        "gameId": 44332,
        "position": 56,
        "isActive": 1
      },
      {
        "gameId": 44452,
        "position": 57,
        "isActive": 1
      },
      {
        "gameId": 45428,
        "position": 58,
        "isActive": 1
      },
      {
        "gameId": 45574,
        "position": 59,
        "isActive": 1
      },
      {
        "gameId": 45693,
        "position": 60,
        "isActive": 1
      },
      {
        "gameId": 46775,
        "position": 61,
        "isActive": 1
      },
      {
        "gameId": 47006,
        "position": 62,
        "isActive": 1
      },
      {
        "gameId": 47007,
        "position": 63,
        "isActive": 1
      },
      {
        "gameId": 47008,
        "position": 64,
        "isActive": 1
      },
      {
        "gameId": 47009,
        "position": 65,
        "isActive": 1
      },
      {
        "gameId": 47010,
        "position": 66,
        "isActive": 1
      },
      {
        "gameId": 47093,
        "position": 67,
        "isActive": 1
      },
      {
        "gameId": 47550,
        "position": 68,
        "isActive": 1
      },
      {
        "gameId": 50153,
        "position": 69,
        "isActive": 1
      },
      {
        "gameId": 50933,
        "position": 70,
        "isActive": 1
      },
      {
        "gameId": 50984,
        "position": 71,
        "isActive": 1
      },
      {
        "gameId": 50995,
        "position": 72,
        "isActive": 1
      },
      {
        "gameId": 51419,
        "position": 73,
        "isActive": 1
      },
      {
        "gameId": 51747,
        "position": 74,
        "isActive": 1
      },
      {
        "gameId": 52381,
        "position": 75,
        "isActive": 1
      },
      {
        "gameId": 53379,
        "position": 76,
        "isActive": 1
      },
      {
        "gameId": 53837,
        "position": 77,
        "isActive": 1
      },
      {
        "gameId": 54174,
        "position": 78,
        "isActive": 1
      },
      {
        "gameId": 54328,
        "position": 79,
        "isActive": 1
      },
      {
        "gameId": 54329,
        "position": 80,
        "isActive": 1
      },
      {
        "gameId": 54330,
        "position": 81,
        "isActive": 1
      },
      {
        "gameId": 54889,
        "position": 82,
        "isActive": 1
      },
      {
        "gameId": 55017,
        "position": 83,
        "isActive": 1
      },
      {
        "gameId": 55306,
        "position": 84,
        "isActive": 1
      },
      {
        "gameId": 55703,
        "position": 85,
        "isActive": 1
      },
      {
        "gameId": 56344,
        "position": 86,
        "isActive": 1
      },
      {
        "gameId": 56941,
        "position": 116,
        "isActive": 1
      },
      {
        "gameId": 56970,
        "position": 117,
        "isActive": 1
      },
      {
        "gameId": 56994,
        "position": 118,
        "isActive": 1
      },
      {
        "gameId": 57516,
        "position": 119,
        "isActive": 1
      },
      {
        "gameId": 57586,
        "position": 120,
        "isActive": 1
      },
      {
        "gameId": 57672,
        "position": 121,
        "isActive": 1
      },
      {
        "gameId": 59372,
        "position": 122,
        "isActive": 1
      },
      {
        "gameId": 59379,
        "position": 123,
        "isActive": 1
      },
      {
        "gameId": 59862,
        "position": 124,
        "isActive": 1
      },
      {
        "gameId": 59895,
        "position": 125,
        "isActive": 1
      },
      {
        "gameId": 60338,
        "position": 126,
        "isActive": 1
      },
      {
        "gameId": 60711,
        "position": 127,
        "isActive": 1
      },
      {
        "gameId": 61019,
        "position": 128,
        "isActive": 1
      },
      {
        "gameId": 61214,
        "position": 129,
        "isActive": 1
      },
      {
        "gameId": 61319,
        "position": 130,
        "isActive": 1
      },
      {
        "gameId": 61376,
        "position": 131,
        "isActive": 1
      },
      {
        "gameId": 62626,
        "position": 132,
        "isActive": 1
      },
      {
        "gameId": 62663,
        "position": 133,
        "isActive": 1
      },
      {
        "gameId": 63124,
        "position": 134,
        "isActive": 1
      },
      {
        "gameId": 63223,
        "position": 135,
        "isActive": 1
      },
      {
        "gameId": 64150,
        "position": 136,
        "isActive": 1
      },
      {
        "gameId": 64488,
        "position": 137,
        "isActive": 1
      },
      {
        "gameId": 64901,
        "position": 138,
        "isActive": 1
      },
      {
        "gameId": 65606,
        "position": 139,
        "isActive": 1
      },
      {
        "gameId": 66338,
        "position": 140,
        "isActive": 1
      },
      {
        "gameId": 66583,
        "position": 141,
        "isActive": 1
      },
      {
        "gameId": 66700,
        "position": 142,
        "isActive": 1
      },
      {
        "gameId": 67164,
        "position": 143,
        "isActive": 1
      },
      {
        "gameId": 67367,
        "position": 144,
        "isActive": 1
      },
      {
        "gameId": 67413,
        "position": 145,
        "isActive": 1
      },
      {
        "gameId": 67487,
        "position": 146,
        "isActive": 1
      },
      {
        "gameId": 67961,
        "position": 147,
        "isActive": 1
      },
      {
        "gameId": 68179,
        "position": 148,
        "isActive": 1
      },
      {
        "gameId": 68192,
        "position": 149,
        "isActive": 1
      },
      {
        "gameId": 68194,
        "position": 150,
        "isActive": 1
      },
      {
        "gameId": 69264,
        "position": 151,
        "isActive": 1
      },
      {
        "gameId": 70471,
        "position": 152,
        "isActive": 1
      },
      {
        "gameId": 70544,
        "position": 153,
        "isActive": 1
      },
      {
        "gameId": 70689,
        "position": 154,
        "isActive": 1
      },
      {
        "gameId": 70730,
        "position": 155,
        "isActive": 1
      },
      {
        "gameId": 71281,
        "position": 156,
        "isActive": 1
      },
      {
        "gameId": 71282,
        "position": 157,
        "isActive": 1
      },
      {
        "gameId": 71413,
        "position": 158,
        "isActive": 1
      },
      {
        "gameId": 71433,
        "position": 159,
        "isActive": 1
      },
      {
        "gameId": 74418,
        "position": 160,
        "isActive": 1
      },
      {
        "gameId": 75114,
        "position": 161,
        "isActive": 1
      },
      {
        "gameId": 75116,
        "position": 162,
        "isActive": 1
      },
      {
        "gameId": 76141,
        "position": 163,
        "isActive": 1
      },
      {
        "gameId": 76350,
        "position": 164,
        "isActive": 1
      },
      {
        "gameId": 77439,
        "position": 165,
        "isActive": 1
      },
      {
        "gameId": 57,
        "position": 166,
        "isActive": 1
      },
      {
        "gameId": 124,
        "position": 167,
        "isActive": 1
      },
      {
        "gameId": 234,
        "position": 168,
        "isActive": 1
      },
      {
        "gameId": 236,
        "position": 169,
        "isActive": 1
      },
      {
        "gameId": 238,
        "position": 170,
        "isActive": 1
      },
      {
        "gameId": 240,
        "position": 171,
        "isActive": 1
      },
      {
        "gameId": 244,
        "position": 172,
        "isActive": 1
      },
      {
        "gameId": 246,
        "position": 173,
        "isActive": 1
      },
      {
        "gameId": 248,
        "position": 174,
        "isActive": 1
      },
      {
        "gameId": 250,
        "position": 175,
        "isActive": 1
      },
      {
        "gameId": 252,
        "position": 176,
        "isActive": 1
      },
      {
        "gameId": 254,
        "position": 177,
        "isActive": 1
      },
      {
        "gameId": 256,
        "position": 178,
        "isActive": 1
      },
      {
        "gameId": 258,
        "position": 179,
        "isActive": 1
      },
      {
        "gameId": 260,
        "position": 180,
        "isActive": 1
      },
      {
        "gameId": 262,
        "position": 181,
        "isActive": 1
      },
      {
        "gameId": 264,
        "position": 182,
        "isActive": 1
      },
      {
        "gameId": 266,
        "position": 183,
        "isActive": 1
      },
      {
        "gameId": 268,
        "position": 184,
        "isActive": 1
      },
      {
        "gameId": 270,
        "position": 185,
        "isActive": 1
      },
      {
        "gameId": 274,
        "position": 186,
        "isActive": 1
      },
      {
        "gameId": 276,
        "position": 187,
        "isActive": 1
      },
      {
        "gameId": 278,
        "position": 188,
        "isActive": 1
      },
      {
        "gameId": 280,
        "position": 189,
        "isActive": 1
      },
      {
        "gameId": 282,
        "position": 190,
        "isActive": 1
      },
      {
        "gameId": 284,
        "position": 191,
        "isActive": 1
      },
      {
        "gameId": 286,
        "position": 192,
        "isActive": 1
      },
      {
        "gameId": 288,
        "position": 193,
        "isActive": 1
      },
      {
        "gameId": 328,
        "position": 194,
        "isActive": 1
      },
      {
        "gameId": 332,
        "position": 195,
        "isActive": 1
      },
      {
        "gameId": 422,
        "position": 196,
        "isActive": 1
      },
      {
        "gameId": 424,
        "position": 197,
        "isActive": 1
      },
      {
        "gameId": 426,
        "position": 198,
        "isActive": 1
      },
      {
        "gameId": 496,
        "position": 199,
        "isActive": 1
      },
      {
        "gameId": 586,
        "position": 200,
        "isActive": 1
      },
      {
        "gameId": 588,
        "position": 201,
        "isActive": 1
      },
      {
        "gameId": 590,
        "position": 202,
        "isActive": 1
      },
      {
        "gameId": 592,
        "position": 203,
        "isActive": 1
      },
      {
        "gameId": 594,
        "position": 204,
        "isActive": 1
      },
      {
        "gameId": 596,
        "position": 205,
        "isActive": 1
      },
      {
        "gameId": 882,
        "position": 206,
        "isActive": 1
      },
      {
        "gameId": 888,
        "position": 207,
        "isActive": 1
      },
      {
        "gameId": 890,
        "position": 208,
        "isActive": 1
      },
      {
        "gameId": 32859,
        "position": 209,
        "isActive": 1
      },
      {
        "gameId": 32861,
        "position": 210,
        "isActive": 1
      },
      {
        "gameId": 32863,
        "position": 211,
        "isActive": 1
      },
      {
        "gameId": 32865,
        "position": 212,
        "isActive": 1
      },
      {
        "gameId": 36183,
        "position": 213,
        "isActive": 1
      },
      {
        "gameId": 36185,
        "position": 214,
        "isActive": 1
      },
      {
        "gameId": 36187,
        "position": 215,
        "isActive": 1
      },
      {
        "gameId": 36189,
        "position": 216,
        "isActive": 1
      },
      {
        "gameId": 36191,
        "position": 217,
        "isActive": 1
      },
      {
        "gameId": 36193,
        "position": 218,
        "isActive": 1
      },
      {
        "gameId": 36195,
        "position": 219,
        "isActive": 1
      },
      {
        "gameId": 37981,
        "position": 220,
        "isActive": 1
      },
      {
        "gameId": 38083,
        "position": 221,
        "isActive": 1
      },
      {
        "gameId": 38093,
        "position": 222,
        "isActive": 1
      },
      {
        "gameId": 47381,
        "position": 223,
        "isActive": 1
      },
      {
        "gameId": 47382,
        "position": 224,
        "isActive": 1
      },
      {
        "gameId": 47383,
        "position": 225,
        "isActive": 1
      },
      {
        "gameId": 47384,
        "position": 226,
        "isActive": 1
      },
      {
        "gameId": 47385,
        "position": 227,
        "isActive": 1
      },
      {
        "gameId": 47386,
        "position": 228,
        "isActive": 1
      },
      {
        "gameId": 47387,
        "position": 229,
        "isActive": 1
      },
      {
        "gameId": 47388,
        "position": 230,
        "isActive": 1
      },
      {
        "gameId": 47389,
        "position": 231,
        "isActive": 1
      },
      {
        "gameId": 47390,
        "position": 232,
        "isActive": 1
      },
      {
        "gameId": 48085,
        "position": 233,
        "isActive": 1
      },
      {
        "gameId": 48086,
        "position": 234,
        "isActive": 1
      },
      {
        "gameId": 50241,
        "position": 235,
        "isActive": 1
      },
      {
        "gameId": 50242,
        "position": 236,
        "isActive": 1
      }
    ]
  }
}